{
  "project_info": {
    "project_number": "1031185131099",
    "firebase_url": "https://elgamalfinancial-default-rtdb.europe-west1.firebasedatabase.app",
    "project_id": "elgamalfinancial",
    "storage_bucket": "elgamalfinancial.firebasestorage.app"
  },
  "client": [
    {
      "client_info": {
        "mobilesdk_app_id": "1:1031185131099:android:f153447deaef64968b817e",
        "android_client_info": {
          "package_name": "com.elgamalcars.elgamal_financial"
        }
      },
      "oauth_client": [],
      "api_key": [
        {
          "current_key": "AIzaSyBA0SrFJL9rHtT8M44LX53HxsAPCm7v0mQ"
        }
      ],
      "services": {
        "appinvite_service": {
          "other_platform_oauth_client": []
        }
      }
    },
    {
      "client_info": {
        "mobilesdk_app_id": "1:1031185131099:android:fb8bf7b8f6f322868b817e",
        "android_client_info": {
          "package_name": "com.example.moneytrack"
        }
      },
      "oauth_client": [],
      "api_key": [
        {
          "current_key": "AIzaSyBA0SrFJL9rHtT8M44LX53HxsAPCm7v0mQ"
        }
      ],
      "services": {
        "appinvite_service": {
          "other_platform_oauth_client": []
        }
      }
    }
  ],
  "configuration_version": "1"
}